blackboxpackage/__init__.py
blackboxpackage/aws.py
blackboxpackage/ftp.py
blackboxpackage/function.py
blackboxpackage/oracle.py
blackboxpackage/postgresql.py
blackboxpackage-0.1.4.dist-info/LICENSE
blackboxpackage-0.1.4.dist-info/METADATA
blackboxpackage-0.1.4.dist-info/WHEEL
blackboxpackage-0.1.4.dist-info/top_level.txt
blackboxpackage-0.1.4.dist-info/RECORD
