Metadata-Version: 2.1
Name: blackboxpackage
Version: 0.1.4
Summary: Pacote de tratamento de dados
Home-page: https://bitbucket.org/ainstec/black-box-package
Author: Ravi Jose Fiori
Author-email: ravi.fiori@concil.com.br
License: MIT
Keywords: Pacote
Platform: UNKNOWN
